signac/__init__.py
signac/__main__.py
signac/_config.py
signac/_dict_manager.py
signac/_search_indexer.py
signac/_utility.py
signac/diff.py
signac/errors.py
signac/filterparse.py
signac/h5store.py
signac/import_export.py
signac/job.py
signac/linked_view.py
signac/project.py
signac/schema.py
signac/sync.py
signac/version.py
signac/_vendor/__init__.py
signac/_vendor/configobj/__init__.py
signac/_vendor/configobj/_version.py
signac/_vendor/configobj/validate.py
signac/_vendor/deprecation/__init__.py
signac/migration/__init__.py
signac/migration/v0_to_v1.py
signac/migration/v1_to_v2.py
signac-2.3.0.dist-info/licenses/LICENSE.txt
signac-2.3.0.dist-info/METADATA
signac-2.3.0.dist-info/WHEEL
signac-2.3.0.dist-info/entry_points.txt
signac-2.3.0.dist-info/top_level.txt
signac-2.3.0.dist-info/RECORD
