Metadata-Version: 2.4
Name: signac
Version: 2.3.0
Summary: Manage large and heterogeneous data spaces on the file system.
Author-email: "Carl Simon Adorf et al." <csadorf@umich.edu>
Maintainer-email: signac Developers <signac-support@umich.edu>
License: BSD 3-Clause License for the software signac.
Project-URL: Homepage, https://signac.readthedocs.io/
Project-URL: Documentation, https://signac.readthedocs.io/
Project-URL: Download, https://pypi.org/project/signac/
Project-URL: Source, https://github.com/glotzerlab/signac
Project-URL: Issues, https://github.com/glotzerlab/signac/issues
Keywords: simulation,database,index,collaboration,workflow
Classifier: Development Status :: 5 - Production/Stable
Classifier: Intended Audience :: Science/Research
Classifier: License :: OSI Approved :: BSD License
Classifier: Topic :: Database
Classifier: Topic :: Scientific/Engineering :: Physics
Classifier: Programming Language :: Python :: 3.8
Classifier: Programming Language :: Python :: 3.9
Classifier: Programming Language :: Python :: 3.10
Classifier: Programming Language :: Python :: 3.11
Classifier: Programming Language :: Python :: 3.12
Classifier: Programming Language :: Python :: Implementation :: CPython
Classifier: Programming Language :: Python :: Implementation :: PyPy
Requires-Python: >=3.8
License-File: LICENSE.txt
Requires-Dist: filelock>=3.0
Requires-Dist: packaging>=15.0
Requires-Dist: synced_collections>=1.0.0
Requires-Dist: tqdm>=4.46.1
Provides-Extra: h5
Requires-Dist: h5py; extra == "h5"
Dynamic: license-file
